README.md
setup.cfg
setup.py
aws_sudo/CommandParser.py
aws_sudo/__init__.py
aws_sudo/testCommandParser.py
aws_sudo.egg-info/PKG-INFO
aws_sudo.egg-info/SOURCES.txt
aws_sudo.egg-info/dependency_links.txt
aws_sudo.egg-info/entry_points.txt
aws_sudo.egg-info/requires.txt
aws_sudo.egg-info/top_level.txt