Metadata-Version: 1.1
Name: aws-sudo
Version: 1.0.7
Summary: sudo but with AWS accounts
Home-page: https://github.com/voytek-solutions/aws-sudo
Author: Wojtek Oledzki
Author-email: contact@voytek.solutions
License: MIT
Keywords: aws,infrastructure,ansible,terraform,packer
Platform: UNKNOWN
Classifier: Development Status :: 3 - Alpha
Classifier: Intended Audience :: Developers
Classifier: Topic :: Software Development :: Build Tools
Classifier: License :: OSI Approved :: MIT License
Classifier: Programming Language :: Python :: 2
Classifier: Programming Language :: Python :: 2.7
Classifier: Programming Language :: Python :: 3
Classifier: Programming Language :: Python :: 3.5
Classifier: Programming Language :: Python :: 3.6
